[
    {
        "opinionId": "6292251",
        "author": "Adio",
        "rcmd": true,
        "stars": 4.5,
        "content": "Fotel \"budżetowy\" więc jak ktoś za tę cenę, ma wysokie wymagania to trzeba popatrzeć co za 300 zł oferuje rynek. W tym przypadku mamy wygodny fotel, z szerokim siedziskiem i regulowanymi podłokietnikami (też szerokimi),  siatkowe \"plecy\" wysokie oparcie. jedynie nie wiem jak latem będzie się sprawował skóropodobny fragment, materiału na końcu siedziska ale to obawy na przyszłość, a może tylko zapewni dłuższą żywotność bez klejenia się do użytkownika?. Dla mnie bardzo dobry produkt w tej cenie. Jestem zadowolony z użytkowania. Mam tej firmy droższy fotel i tez jestem zadowolony. Polecam.",
        "pros": [
            "jakość",
            "regulowane podlokietniki",
            "siatkowe",
            "wygląd",
            "wygoda"
        ],
        "cons": [],
        "purchased": true,
        "publishDate": "2017-12-05 08:45:07",
        "purchaseDate": "2017-10-26 22:39:44",
        "usefull": 0,
        "useless": 0
    },
    {
        "opinionId": "10221637",
        "author": "Filip",
        "rcmd": true,
        "stars": 5.0,
        "content": "Pracuje mi się na nim tak, jak powinno; proste plecy podparte na odcinku lędźwiowym, łokcie na podłokietnikach, których regulacja rzadko się zdarza w solidnych krzesłach poniżej pewnej kwoty. Jedyne, co wydaje mi się bezcelowe, to skóra pośrodku siedziska, czyli dokładnie tam, gdzie powinien być przewiew.",
        "pros": [
            "jakość",
            "regulowane podlokietniki",
            "siatkowe",
            "wygląd",
            "wygoda"
        ],
        "cons": [],
        "purchased": true,
        "publishDate": "2019-03-10 23:56:02",
        "purchaseDate": "2019-02-07 12:54:43",
        "usefull": 0,
        "useless": 0
    },
    {
        "opinionId": "6348104",
        "author": "agaspox",
        "rcmd": true,
        "stars": 5.0,
        "content": "Fotel dobrze wykonany, stabilna konstrukcja. Wygodny, możliwość regulacji wysokości siedzenia oraz podłokietników, Przewieny siatkowy materiał odporny na zabrudzenia I łatwy w szyszczrniu. Dobrze wyprofilowane oparcie dające komfort przy długotrwałej pracy w pozycji siedzącej. Serdecznie polecam.",
        "pros": [
            "jakość",
            "regulowane podlokietniki",
            "siatkowe",
            "wygląd",
            "wygoda"
        ],
        "cons": [],
        "purchased": true,
        "publishDate": "2017-12-15 10:25:01",
        "purchaseDate": "2017-11-16 13:06:24",
        "usefull": 0,
        "useless": 0
    },
    {
        "opinionId": "8414185",
        "author": "haurus",
        "rcmd": true,
        "stars": 5.0,
        "content": "Za tę cene krzesło jest GENIALNE, podłokietniki wydają się być troche delikatne i krzesło lekko buja się na boki, ale jak za tą cenę to takie coś nic nie znaczy. Świetne krzesło zwłaszcza dla wysokich osób.",
        "pros": [
            "jakość",
            "regulowane podlokietniki",
            "siatkowe",
            "wygląd",
            "wygoda"
        ],
        "cons": [],
        "purchased": true,
        "publishDate": "2018-10-05 14:41:37",
        "purchaseDate": "2018-09-09 20:59:59",
        "usefull": 1,
        "useless": 0
    },
    {
        "opinionId": "6642356",
        "author": "Piotr",
        "rcmd": true,
        "stars": 4.5,
        "content": "Świetny stosunek jakość - cena, łatwy i szybki montaż.  Szkoda tylko że nie ma możliwości blokady mechanizmu bujania w wybranej pozycji.",
        "pros": [
            "jakość",
            "regulowane podlokietniki",
            "siatkowe",
            "wygląd"
        ],
        "cons": [],
        "purchased": true,
        "publishDate": "2018-02-26 11:51:59",
        "purchaseDate": "2018-01-28 18:13:11",
        "usefull": 0,
        "useless": 0
    },
    {
        "opinionId": "4158292",
        "author": "minio3377",
        "rcmd": true,
        "stars": 4.5,
        "content": "Korzystna relacja jakości do ceny, wygodny, dość ciekawe wzornictwo, nie skrzypi! Użytkowany przez syna w wieku 11 lat, jest zadowolony, warto było dołożyć parędziesiąt pln więcej.",
        "pros": [],
        "cons": [],
        "purchased": true,
        "publishDate": "2016-11-06 15:54:50",
        "purchaseDate": "2016-09-23 20:28:19",
        "usefull": 0,
        "useless": 0
    },
    {
        "opinionId": "4819828",
        "author": "Ryniu",
        "rcmd": true,
        "stars": 4.0,
        "content": "Bardzo wygodne krzesło jak za tę cenę. Osoby ze wzrostem powyżej 190 cm nie oprą głowy o oparcie przy prostej postawie.  Złożenie banalnie proste, nie potrzeba swoich narzędzi.",
        "pros": [],
        "cons": [],
        "purchased": true,
        "publishDate": "2017-07-05 09:48:48",
        "purchaseDate": "2017-06-05 00:51:44",
        "usefull": 0,
        "useless": 0
    },
    {
        "opinionId": "4733960",
        "author": "Użytkownik Ceneo",
        "rcmd": true,
        "stars": 4.0,
        "content": "Fotel wygodny, solidnie wykonany. Oparcie w formie siatki zapobiega poceniu. Może siedzisko nieco twarde, ale po dokupieniu poduchy, jest ok. Polecam!",
        "pros": [],
        "cons": [],
        "purchased": true,
        "publishDate": "2017-06-06 17:20:30",
        "purchaseDate": "2017-04-20 00:12:24",
        "usefull": 0,
        "useless": 0
    },
    {
        "opinionId": "10120357",
        "author": "K...a",
        "rcmd": null,
        "stars": 3.5,
        "content": "słabe plastiki - w kilku szt. dotarły popękane. Siatka pęka i pruje się na końcach stelaża oparcia",
        "pros": [
            "regulowane podlokietniki",
            "wygląd",
            "wygoda"
        ],
        "cons": [
            "jakość"
        ],
        "purchased": true,
        "publishDate": "2019-02-19 10:38:15",
        "purchaseDate": "2019-01-21 10:43:22",
        "usefull": 0,
        "useless": 0
    },
    {
        "opinionId": "8246899",
        "author": "Chimney343",
        "rcmd": false,
        "stars": 2.0,
        "content": "Plusy:  - bardzo wygodne, dobrze wyprofilowane siedzisko z oddychającego materiału  - chromowana, solidna gwiazda  - dla osoby o wzroście 165-170: idealna wysokość i profil oparcia. Dla kogoś 175+ - niestety, ale ni cholery nie można oprzeć głowy bez odchylania się do tyłu.   - łatwy w montażu  - solidna siatka oparcia    Minusy:  - podłokietniki o regulowanej wysokości mają luzy i telepią się jak szalone, bez włożenia kawałka gazety czy tekturki można dostać szału  - bardzo słabo przygotowane otwory na śruby   - SKRZYPI. Być może po potraktowaniu WD-40 skrzypiałby mniej, ale nie sprawdzałem.   Wydaje mi się, że ten model, Halmar Vire i Nowy Styl Fotel Hit to wszystko jedna i ta sama chińszczyzna - podobne siedzisko i profil oparcia. Ten Grospolu jest pewnie droższy, bo ma regulowane podłokietniki.",
        "pros": [
            "jakość",
            "wygląd"
        ],
        "cons": [
            "regulowane podlokietniki",
            "siatkowe",
            "wygoda"
        ],
        "purchased": true,
        "publishDate": "2018-08-14 17:42:45",
        "purchaseDate": "2018-07-19 11:04:43",
        "usefull": 2,
        "useless": 0
    },
    {
        "opinionId": "6659871",
        "author": "Użytkownik Ceneo",
        "rcmd": true,
        "stars": 4.5,
        "content": "Duży, wygodny, miękkie regulowane podłokietniki. Bardzo głębokie siedzisko, nie dla niskich osób.",
        "pros": [
            "jakość",
            "regulowane podlokietniki",
            "siatkowe",
            "wygląd"
        ],
        "cons": [],
        "purchased": true,
        "publishDate": "2018-03-01 11:12:52",
        "purchaseDate": "2018-02-21 13:47:46",
        "usefull": 0,
        "useless": 0
    },
    {
        "opinionId": "10831113",
        "author": "M...j",
        "rcmd": true,
        "stars": 5.0,
        "content": "Jeżeli ktoś szuka dobrego i taniego fotela do farming'u czy do pracy to ten fotel jest idealny.",
        "pros": [
            "czaami skrzypi",
            "jakość",
            "-jakość",
            "-materiał siateczkowy",
            "regulowane podlokietniki",
            "-regulowane podłokietniki",
            "siatkowe",
            "wygląd",
            "-wygląd",
            "wygoda",
            "-wygoda"
        ],
        "cons": [],
        "purchased": true,
        "publishDate": "2019-07-25 09:58:59",
        "purchaseDate": "2019-06-26 12:32:06",
        "usefull": 0,
        "useless": 0
    },
    {
        "opinionId": "14157171",
        "author": "w...l",
        "rcmd": true,
        "stars": 5.0,
        "content": "ładne, estetyczne, wygodne, ergonomiczne, nie skrzypi, krzesło 'oddychające'. Super wybór.",
        "pros": [
            "jakość",
            "łatwy montaż",
            "regulowane podlokietniki",
            "siatkowe",
            "stabilne",
            "wygląd",
            "wygoda"
        ],
        "cons": [
            "brak"
        ],
        "purchased": true,
        "publishDate": "2021-03-22 11:45:16",
        "purchaseDate": "2021-02-21 12:02:02",
        "usefull": 0,
        "useless": 0
    },
    {
        "opinionId": "8779050",
        "author": "jm",
        "rcmd": true,
        "stars": 4.5,
        "content": "nie ma możliwości zablokowania odgięcia do tyłu. poza tym super za te pieniądze.",
        "pros": [
            "jakość",
            "regulowane podlokietniki",
            "siatkowe",
            "wygląd",
            "wygoda"
        ],
        "cons": [],
        "purchased": true,
        "publishDate": "2018-12-20 11:39:13",
        "purchaseDate": "2018-11-20 20:23:49",
        "usefull": 0,
        "useless": 0
    },
    {
        "opinionId": "8435808",
        "author": "Ula",
        "rcmd": true,
        "stars": 5.0,
        "content": "fotel w zupełności spełnił moje oczekiwania , jest wygodny po prostu super",
        "pros": [
            "jakość",
            "regulowane podlokietniki",
            "siatkowe",
            "wygląd",
            "wygoda"
        ],
        "cons": [],
        "purchased": true,
        "publishDate": "2018-10-12 11:50:30",
        "purchaseDate": "2018-09-12 12:18:12",
        "usefull": 0,
        "useless": 0
    },
    {
        "opinionId": "10924429",
        "author": "Lukasz",
        "rcmd": true,
        "stars": 4.0,
        "content": "Krzesłko ogólnie ok z tym że odchylenie do tyłu nie działa u mnie na stałe tylko podczas siedzenia można się 'powyginać'",
        "pros": [],
        "cons": [],
        "purchased": true,
        "publishDate": "2019-08-16 10:55:39",
        "purchaseDate": "2019-07-17 22:31:02",
        "usefull": 0,
        "useless": 0
    },
    {
        "opinionId": "10630759",
        "author": "caleb59",
        "rcmd": true,
        "stars": 5.0,
        "content": "W segmencie cenowym nieco powyżej 300zł chyba nie ma lepszego wyboru.",
        "pros": [
            "jakość",
            "regulowane podlokietniki",
            "siatkowe",
            "wygląd"
        ],
        "cons": [
            "wygoda"
        ],
        "purchased": true,
        "publishDate": "2019-06-07 14:22:28",
        "purchaseDate": "2019-04-30 18:23:24",
        "usefull": 0,
        "useless": 0
    },
    {
        "opinionId": "6438444",
        "author": "Dorota",
        "rcmd": true,
        "stars": 5.0,
        "content": "wygodne,  dopasowane do kształtu ciała, bezproblemowo się przesuwa.",
        "pros": [
            "czaami skrzypi",
            "jakość",
            "regulowane podlokietniki",
            "siatkowe",
            "wygląd",
            "wygoda"
        ],
        "cons": [],
        "purchased": true,
        "publishDate": "2018-01-05 11:22:20",
        "purchaseDate": "2017-11-28 10:09:42",
        "usefull": 0,
        "useless": 0
    },
    {
        "opinionId": "8365299",
        "author": "MISIEK",
        "rcmd": true,
        "stars": 4.0,
        "content": "KRZESŁO SOLIDNE I DOBRZE WYGLĄDAJĄCE. CO DO WYGODY TO PRZYDAŁOBY SIĘ GŁĘBSZE WYPROFILOWANIE OKOLICY LĘDŹWIOWEJ.",
        "pros": [],
        "cons": [],
        "purchased": true,
        "publishDate": "2018-09-20 15:12:49",
        "purchaseDate": "2018-08-21 15:42:48",
        "usefull": 0,
        "useless": 0
    },
    {
        "opinionId": "13888882",
        "author": "s...2",
        "rcmd": false,
        "stars": 2.0,
        "content": "Transakcja w sklepie poszła szybko i sprawnie i profesjonalnie ale jeśli chodzi o sam produkt to troche jestem zawiedziony, krzesło troche sie huśta i skrzypi, coś musi być z tą rurą pod siedziskiem, zobaczę co i jak zgłosze to.",
        "pros": [],
        "cons": [],
        "purchased": true,
        "publishDate": "2021-02-03 11:56:59",
        "purchaseDate": "2020-10-25 10:56:28",
        "usefull": 0,
        "useless": 0
    },
    {
        "opinionId": "13124750",
        "author": "a...a",
        "rcmd": true,
        "stars": 4.0,
        "content": "Krzeslo super, jedynie cześć lędźwiowa mogłaby mieć większy zakres regulacji. Dla mnie jest trochę za wysoko.",
        "pros": [
            "jakość",
            "regulowane podlokietniki",
            "wygląd"
        ],
        "cons": [
            "wygoda"
        ],
        "purchased": true,
        "publishDate": "2020-09-24 21:11:24",
        "purchaseDate": "2020-08-19 17:37:19",
        "usefull": 0,
        "useless": 0
    },
    {
        "opinionId": "8064320",
        "author": "agaspox",
        "rcmd": true,
        "stars": 5.0,
        "content": "Super fotel wygodny I komfortowy za rozsądne pieniądze",
        "pros": [],
        "cons": [],
        "purchased": true,
        "publishDate": "2018-06-20 11:23:39",
        "purchaseDate": "2018-05-21 11:57:41",
        "usefull": 0,
        "useless": 0
    },
    {
        "opinionId": "8320887",
        "author": "Krzysztof",
        "rcmd": true,
        "stars": 5.0,
        "content": "Po ponad miesiącu użytkowania. Jestem zadowolony.",
        "pros": [
            "regulowane podlokietniki",
            "siatkowe",
            "wygląd",
            "wygoda"
        ],
        "cons": [],
        "purchased": true,
        "publishDate": "2018-09-06 10:03:49",
        "purchaseDate": "2018-08-07 12:59:43",
        "usefull": 0,
        "useless": 0
    },
    {
        "opinionId": "6699284",
        "author": "Waldek",
        "rcmd": true,
        "stars": 4.0,
        "content": "Krzesło wygodne, solidnie wykonane. Po 1 miesiącu użytkowania nie mam żadnych zastrzeżeń. Polecam",
        "pros": [],
        "cons": [],
        "purchased": true,
        "publishDate": "2018-03-12 11:18:55",
        "purchaseDate": "2018-02-02 15:03:19",
        "usefull": 0,
        "useless": 0
    },
    {
        "opinionId": "6248168",
        "author": "Kamil",
        "rcmd": true,
        "stars": 5.0,
        "content": "Ogólnie dobry i wygodny fotel. Zdecydowałem się zamówić szerszy i wyższy, dlatego zwróciłem.,",
        "pros": [],
        "cons": [],
        "purchased": true,
        "publishDate": "2017-11-23 23:45:40",
        "purchaseDate": "2017-10-24 08:50:43",
        "usefull": 0,
        "useless": 0
    },
    {
        "opinionId": "11080827",
        "author": "Anna",
        "rcmd": true,
        "stars": 5.0,
        "content": "bardao dobree spełnia moje oczekiwania",
        "pros": [
            "jakość",
            "regulowane podlokietniki",
            "siatkowe",
            "wygląd",
            "wygoda"
        ],
        "cons": [],
        "purchased": true,
        "publishDate": "2019-09-25 16:41:29",
        "purchaseDate": "2019-08-26 12:01:07",
        "usefull": 0,
        "useless": 0
    },
    {
        "opinionId": "11176587",
        "author": "Tomasz",
        "rcmd": true,
        "stars": 5.0,
        "content": "Fotel bardzo wygodny i funkcjonalny.",
        "pros": [
            "czaami skrzypi",
            "jakość",
            "regulowane podlokietniki",
            "siatkowe",
            "wygląd",
            "wygoda"
        ],
        "cons": [],
        "purchased": true,
        "publishDate": "2019-10-20 08:15:45",
        "purchaseDate": "2019-10-12 18:48:42",
        "usefull": 0,
        "useless": 0
    },
    {
        "opinionId": "4138983",
        "author": "Anna",
        "rcmd": true,
        "stars": 5.0,
        "content": "Fantastyczne Wygodne jak nigdy, pełna regulacja, jeden z najlepszych zakupów  życiu!",
        "pros": [],
        "cons": [],
        "purchased": true,
        "publishDate": "2016-11-01 21:03:47",
        "purchaseDate": "2016-09-26 22:39:10",
        "usefull": 0,
        "useless": 0
    },
    {
        "opinionId": "12963964",
        "author": "e...b",
        "rcmd": true,
        "stars": 5.0,
        "content": "Spelnia moje oczekiwania, jest wygodne, nie bola mnie plecy po siedzeniu 8 godzin.",
        "pros": [],
        "cons": [],
        "purchased": true,
        "publishDate": "2020-08-17 12:23:55",
        "purchaseDate": "2020-07-17 11:22:36",
        "usefull": 0,
        "useless": 0
    },
    {
        "opinionId": "11007214",
        "author": "Halina",
        "rcmd": true,
        "stars": 5.0,
        "content": "Grospol Fotel Plus R 3908  jest ergonomiczny , estetyczny, spełnia oczekiwania",
        "pros": [],
        "cons": [],
        "purchased": true,
        "publishDate": "2019-09-05 13:03:41",
        "purchaseDate": "2019-08-06 09:51:22",
        "usefull": 0,
        "useless": 0
    },
    {
        "opinionId": "12650079",
        "author": "d...j",
        "rcmd": true,
        "stars": 4.5,
        "content": "Minusem jest brak możliwości swobodnego regulowania poziomu nachylenia oparcia.",
        "pros": [
            "jakość",
            "regulowane podlokietniki",
            "wygląd",
            "wygoda"
        ],
        "cons": [],
        "purchased": true,
        "publishDate": "2020-06-15 16:01:51",
        "purchaseDate": "2020-05-15 10:14:28",
        "usefull": 0,
        "useless": 0
    },
    {
        "opinionId": "6394676",
        "author": "wojtas",
        "rcmd": true,
        "stars": 4.0,
        "content": "Wygodny fotel za te pieniądze",
        "pros": [
            "jakość",
            "regulowane podlokietniki",
            "siatkowe",
            "wygląd",
            "wygoda"
        ],
        "cons": [],
        "purchased": true,
        "publishDate": "2017-12-27 09:52:09",
        "purchaseDate": "2017-11-24 12:09:37",
        "usefull": 0,
        "useless": 0
    },
    {
        "opinionId": "7999122",
        "author": "agaspox",
        "rcmd": true,
        "stars": 5.0,
        "content": "Super jakość w super cenie",
        "pros": [],
        "cons": [],
        "purchased": true,
        "publishDate": "2018-05-29 09:27:30",
        "purchaseDate": "2018-04-26 09:57:17",
        "usefull": 0,
        "useless": 0
    },
    {
        "opinionId": "8428727",
        "author": "Łukasz",
        "rcmd": true,
        "stars": 4.0,
        "content": "produkt zgodny z opisem.",
        "pros": [
            "regulowane podlokietniki",
            "siatkowe",
            "wygląd",
            "wygoda"
        ],
        "cons": [],
        "purchased": true,
        "publishDate": "2018-10-10 18:22:43",
        "purchaseDate": "2018-09-05 20:06:58",
        "usefull": 0,
        "useless": 0
    },
    {
        "opinionId": "5903541",
        "author": "Robert",
        "rcmd": true,
        "stars": 5.0,
        "content": "Za tą cenę to najlepsza propozycja. Jakościowo i funkcjonalnie bez uwag.",
        "pros": [],
        "cons": [],
        "purchased": true,
        "publishDate": "2017-11-16 12:34:44",
        "purchaseDate": "2017-10-17 11:50:59",
        "usefull": 0,
        "useless": 0
    },
    {
        "opinionId": "13126607",
        "author": "g...5",
        "rcmd": true,
        "stars": 4.5,
        "content": "Produkt godny ceny, wykonanie super, wygoda siedzenia. Polecam każdemu.",
        "pros": [
            "czaami skrzypi",
            "jakość",
            "-jakość",
            "regulowane podlokietniki",
            "siatkowe",
            "wygląd",
            "-wygląd",
            "wygoda"
        ],
        "cons": [],
        "purchased": true,
        "publishDate": "2020-09-25 10:01:41",
        "purchaseDate": "2020-08-27 11:23:50",
        "usefull": 0,
        "useless": 0
    },
    {
        "opinionId": "4546458",
        "author": "Marcin",
        "rcmd": true,
        "stars": 4.0,
        "content": "wszystko ok, krzesło nie ma jedynie blokady w pozycji wygiętej",
        "pros": [],
        "cons": [],
        "purchased": true,
        "publishDate": "2017-04-05 11:29:17",
        "purchaseDate": "2017-02-28 12:44:31",
        "usefull": 0,
        "useless": 0
    },
    {
        "opinionId": "8620036",
        "author": "Wanda",
        "rcmd": true,
        "stars": 5.0,
        "content": "bardzo ok!",
        "pros": [
            "jakość",
            "regulowane podlokietniki",
            "siatkowe",
            "wygląd",
            "wygoda"
        ],
        "cons": [],
        "purchased": true,
        "publishDate": "2018-11-27 11:06:23",
        "purchaseDate": "2018-10-23 10:51:51",
        "usefull": 0,
        "useless": 0
    },
    {
        "opinionId": "8246094",
        "author": "Asia",
        "rcmd": true,
        "stars": 5.0,
        "content": "Rewelacyjny produkt i pełne zadowolenie z obsługi i dostawy.",
        "pros": [],
        "cons": [],
        "purchased": true,
        "publishDate": "2018-08-14 13:08:46",
        "purchaseDate": "2018-07-02 13:19:21",
        "usefull": 0,
        "useless": 0
    },
    {
        "opinionId": "8362347",
        "author": "Krzysztof",
        "rcmd": false,
        "stars": 1.5,
        "content": "Skusiłem się na zakup po przeczytaniu opinii i bardzo się rozczarowałem. Fotel jest koszmarnie niewygodny (i nie jest to wyłącznie moje zdanie). W pozycji zablokowanej oparcie jest pod kątem prostym w stosunku do siedziska, które jest beznadziejnie wyprofilowane - przód idzie ku dołowi. Nie da się zablokować oparcia w pozycji odchylonej. Ogólnie wysiedzenie na tym wynalazku dłużej niż kilkadziesiąt minut to sztuka. Do tego jakość wykonania pozostawia trochę do życzenia - np. podłokietniki, które po przykręceniu są pod różnymi kątami do oparcia. Ogólnie nie polecam. 1,5 gwiazdki wyłączni za estetyczny wygląd i cenę, która jednak i tak jest za wysoko w stosunku do tego, co się dostaje.",
        "pros": [
            "wygląd"
        ],
        "cons": [
            "jakość"
        ],
        "purchased": false,
        "publishDate": "2018-09-19 21:19:36",
        "purchaseDate": null,
        "usefull": 1,
        "useless": 0
    },
    {
        "opinionId": "5061849",
        "author": "Przemek",
        "rcmd": true,
        "stars": 4.5,
        "content": "daje rade",
        "pros": [
            "jakość",
            "regulowane podlokietniki",
            "siatkowe",
            "wygląd",
            "wygoda"
        ],
        "cons": [],
        "purchased": true,
        "publishDate": "2017-09-21 17:31:32",
        "purchaseDate": "2017-08-08 12:44:03",
        "usefull": 0,
        "useless": 0
    },
    {
        "opinionId": "8189857",
        "author": "Pietass",
        "rcmd": true,
        "stars": 5.0,
        "content": "Polecam.",
        "pros": [
            "jakość",
            "regulowane podlokietniki",
            "siatkowe",
            "wygląd",
            "wygoda"
        ],
        "cons": [],
        "purchased": true,
        "publishDate": "2018-07-28 22:39:09",
        "purchaseDate": "2018-07-01 20:37:05",
        "usefull": 0,
        "useless": 0
    },
    {
        "opinionId": "8873009",
        "author": "Justyna",
        "rcmd": true,
        "stars": 5.0,
        "content": "Polecam",
        "pros": [
            "jakość",
            "regulowane podlokietniki",
            "siatkowe",
            "wygląd",
            "wygoda"
        ],
        "cons": [],
        "purchased": true,
        "publishDate": "2019-01-06 12:42:11",
        "purchaseDate": "2018-12-13 13:16:27",
        "usefull": 0,
        "useless": 0
    },
    {
        "opinionId": "8960572",
        "author": "Tomasz",
        "rcmd": true,
        "stars": 5.0,
        "content": "Super",
        "pros": [
            "jakość",
            "regulowane podlokietniki",
            "siatkowe",
            "wygląd",
            "wygoda"
        ],
        "cons": [],
        "purchased": true,
        "publishDate": "2019-01-21 08:27:59",
        "purchaseDate": "2018-12-06 17:32:59",
        "usefull": 0,
        "useless": 0
    },
    {
        "opinionId": "8631378",
        "author": "Danusia",
        "rcmd": true,
        "stars": 5.0,
        "content": "Super",
        "pros": [
            "regulowane podlokietniki",
            "siatkowe",
            "wygoda"
        ],
        "cons": [],
        "purchased": true,
        "publishDate": "2018-11-28 19:13:24",
        "purchaseDate": "2018-10-29 08:17:12",
        "usefull": 0,
        "useless": 0
    },
    {
        "opinionId": "12176857",
        "author": "Użytkownik Ceneo",
        "rcmd": true,
        "stars": 5.0,
        "content": "Dobra jakość, funkcjonalny fotel, w tej cenie polecam.",
        "pros": [],
        "cons": [],
        "purchased": true,
        "publishDate": "2020-04-17 11:34:20",
        "purchaseDate": "2020-03-17 10:10:12",
        "usefull": 0,
        "useless": 0
    },
    {
        "opinionId": "10375733",
        "author": "Ziena",
        "rcmd": null,
        "stars": 3.5,
        "content": "Ogólnie dobrze z małymi problemami o których pisałem",
        "pros": [],
        "cons": [],
        "purchased": true,
        "publishDate": "2019-04-10 11:56:18",
        "purchaseDate": "2019-03-10 14:45:16",
        "usefull": 0,
        "useless": 0
    },
    {
        "opinionId": "12474501",
        "author": "m...a",
        "rcmd": true,
        "stars": 5.0,
        "content": ":)",
        "pros": [
            "jakość",
            "regulowane podlokietniki",
            "wygląd",
            "wygoda"
        ],
        "cons": [],
        "purchased": true,
        "publishDate": "2020-05-20 16:19:56",
        "purchaseDate": "2020-04-20 12:26:03",
        "usefull": 0,
        "useless": 0
    },
    {
        "opinionId": "11501620",
        "author": "aąbcć",
        "rcmd": null,
        "stars": 3.5,
        "content": "ok",
        "pros": [
            "jakość",
            "regulowane podlokietniki",
            "siatkowe",
            "wygląd"
        ],
        "cons": [
            "wygoda"
        ],
        "purchased": true,
        "publishDate": "2019-12-30 07:36:49",
        "purchaseDate": "2019-11-28 13:01:21",
        "usefull": 0,
        "useless": 0
    },
    {
        "opinionId": "8388442",
        "author": "gżehu",
        "rcmd": true,
        "stars": 4.0,
        "content": "ok",
        "pros": [
            "jakość",
            "regulowane podlokietniki",
            "siatkowe",
            "wygląd",
            "wygoda"
        ],
        "cons": [
            "czaami skrzypi"
        ],
        "purchased": true,
        "publishDate": "2018-09-28 10:06:01",
        "purchaseDate": "2018-08-22 17:00:51",
        "usefull": 0,
        "useless": 0
    },
    {
        "opinionId": "4429186",
        "author": "andrzej",
        "rcmd": null,
        "stars": 3.5,
        "content": "drugi raz bym nie kupił, ale za tą cenę może być",
        "pros": [],
        "cons": [],
        "purchased": true,
        "publishDate": "2017-02-14 09:40:18",
        "purchaseDate": "2017-01-16 21:13:34",
        "usefull": 0,
        "useless": 0
    },
    {
        "opinionId": "8418907",
        "author": "Waldemar",
        "rcmd": true,
        "stars": 4.0,
        "content": "brak regulacji odsunięcia oparcia od siedziska",
        "pros": [],
        "cons": [],
        "purchased": true,
        "publishDate": "2018-10-08 09:26:22",
        "purchaseDate": "2018-09-07 11:17:51",
        "usefull": 0,
        "useless": 0
    },
    {
        "opinionId": "4870943",
        "author": "kasia",
        "rcmd": true,
        "stars": 4.0,
        "content": "Wygodne fajnie wygląda i dobra jakość produktu",
        "pros": [],
        "cons": [],
        "purchased": true,
        "publishDate": "2017-07-21 00:03:00",
        "purchaseDate": "2017-06-05 19:25:20",
        "usefull": 0,
        "useless": 0
    },
    {
        "opinionId": "4329307",
        "author": "Adam",
        "rcmd": true,
        "stars": 4.0,
        "content": "Całkiem wygodne krzesło jak na swoją cenę",
        "pros": [],
        "cons": [],
        "purchased": true,
        "publishDate": "2017-01-04 11:23:46",
        "purchaseDate": "2016-11-09 10:02:06",
        "usefull": 0,
        "useless": 0
    },
    {
        "opinionId": "11735041",
        "author": "Użytkownik Ceneo",
        "rcmd": true,
        "stars": 5.0,
        "content": "idealne do biura, w bardzo dobrej cenie",
        "pros": [],
        "cons": [],
        "purchased": true,
        "publishDate": "2020-02-13 09:57:39",
        "purchaseDate": "2020-01-15 15:12:28",
        "usefull": 0,
        "useless": 0
    },
    {
        "opinionId": "8961607",
        "author": "Justyna",
        "rcmd": true,
        "stars": 5.0,
        "content": "krzesło stabilne, regulowane, wysokie:)",
        "pros": [],
        "cons": [],
        "purchased": true,
        "publishDate": "2019-01-21 10:52:19",
        "purchaseDate": "2019-01-16 15:31:14",
        "usefull": 0,
        "useless": 0
    },
    {
        "opinionId": "13427543",
        "author": "a...o",
        "rcmd": true,
        "stars": 5.0,
        "content": "FOTEL BIUROWY SPEŁNIA MOJE OCZEKIWANIA",
        "pros": [
            "jakość",
            "regulowane podlokietniki",
            "wygląd",
            "wygoda"
        ],
        "cons": [],
        "purchased": true,
        "publishDate": "2020-11-23 09:58:24",
        "purchaseDate": "2020-10-22 05:53:09",
        "usefull": 0,
        "useless": 0
    },
    {
        "opinionId": "13122817",
        "author": "g...k",
        "rcmd": true,
        "stars": 5.0,
        "content": "Fotel wygodny w bardzo dobrej cenie",
        "pros": [],
        "cons": [],
        "purchased": true,
        "publishDate": "2020-09-24 13:26:37",
        "purchaseDate": "2020-08-26 19:13:15",
        "usefull": 0,
        "useless": 0
    },
    {
        "opinionId": "4913773",
        "author": "tommy24",
        "rcmd": true,
        "stars": 5.0,
        "content": "Dobre krzesło, w przystępnej cenie.",
        "pros": [],
        "cons": [],
        "purchased": true,
        "publishDate": "2017-08-04 00:08:23",
        "purchaseDate": "2017-07-03 14:51:57",
        "usefull": 0,
        "useless": 0
    },
    {
        "opinionId": "13975708",
        "author": "e...1",
        "rcmd": true,
        "stars": 5.0,
        "content": "Krzesła doskonale , polecam w 100%",
        "pros": [],
        "cons": [],
        "purchased": true,
        "publishDate": "2021-02-17 22:17:54",
        "purchaseDate": "2021-01-18 08:34:45",
        "usefull": 0,
        "useless": 0
    },
    {
        "opinionId": "12560425",
        "author": "m...1",
        "rcmd": true,
        "stars": 5.0,
        "content": "Dobre wykonanie, bardzo wygodny",
        "pros": [],
        "cons": [],
        "purchased": true,
        "publishDate": "2020-06-01 09:19:07",
        "purchaseDate": "2020-05-01 18:56:34",
        "usefull": 0,
        "useless": 0
    },
    {
        "opinionId": "8515649",
        "author": "1966marti",
        "rcmd": true,
        "stars": 5.0,
        "content": "Dostałam to czego oczekiwałam",
        "pros": [],
        "cons": [],
        "purchased": true,
        "publishDate": "2018-11-04 15:32:17",
        "purchaseDate": "2018-10-03 13:24:48",
        "usefull": 0,
        "useless": 0
    },
    {
        "opinionId": "13752003",
        "author": "h...a",
        "rcmd": true,
        "stars": 4.5,
        "content": "Za taką cenę to jest super",
        "pros": [
            "jakość",
            "-jakość",
            "regulowane podlokietniki",
            "-regulowane podłokietniki",
            "wygląd",
            "-wygląd",
            "wygoda",
            "-wygoda"
        ],
        "cons": [],
        "purchased": true,
        "publishDate": "2021-01-12 08:14:51",
        "purchaseDate": "2020-12-10 14:52:44",
        "usefull": 0,
        "useless": 0
    },
    {
        "opinionId": "12000586",
        "author": "Użytkownik Ceneo",
        "rcmd": true,
        "stars": 5.0,
        "content": "cena adekwatna do jakości",
        "pros": [],
        "cons": [],
        "purchased": true,
        "publishDate": "2020-03-27 12:54:00",
        "purchaseDate": "2020-02-27 12:18:57",
        "usefull": 0,
        "useless": 0
    },
    {
        "opinionId": "4570512",
        "author": "Grzegorz",
        "rcmd": true,
        "stars": 4.0,
        "content": "Dobra relacja cena -towar",
        "pros": [],
        "cons": [],
        "purchased": true,
        "publishDate": "2017-04-13 19:03:33",
        "purchaseDate": "2017-04-07 18:25:22",
        "usefull": 0,
        "useless": 0
    },
    {
        "opinionId": "4547019",
        "author": "mareQ",
        "rcmd": true,
        "stars": 5.0,
        "content": "zgodnie z opisem na *****",
        "pros": [],
        "cons": [],
        "purchased": true,
        "publishDate": "2017-04-05 12:59:42",
        "purchaseDate": "2017-03-07 09:39:19",
        "usefull": 0,
        "useless": 0
    },
    {
        "opinionId": "12936055",
        "author": "p...a",
        "rcmd": true,
        "stars": 4.5,
        "content": "wygodne krzeslo, polecam",
        "pros": [],
        "cons": [],
        "purchased": true,
        "publishDate": "2020-08-11 10:43:21",
        "purchaseDate": "2020-07-13 13:38:12",
        "usefull": 0,
        "useless": 0
    },
    {
        "opinionId": "11940410",
        "author": "Użytkownik Ceneo",
        "rcmd": true,
        "stars": 5.0,
        "content": "Spełnia moje oczekiwania",
        "pros": [],
        "cons": [],
        "purchased": true,
        "publishDate": "2020-03-19 11:57:03",
        "purchaseDate": "2020-02-19 11:07:33",
        "usefull": 0,
        "useless": 0
    },
    {
        "opinionId": "11792957",
        "author": "Użytkownik Ceneo",
        "rcmd": true,
        "stars": 5.0,
        "content": "Spełnia moje oczekiwania",
        "pros": [],
        "cons": [],
        "purchased": true,
        "publishDate": "2020-02-24 07:21:01",
        "purchaseDate": "2020-01-16 14:42:37",
        "usefull": 0,
        "useless": 0
    },
    {
        "opinionId": "4552147",
        "author": "Agnieszka",
        "rcmd": true,
        "stars": 5.0,
        "content": "zgodnie z oczekiwaniem",
        "pros": [],
        "cons": [],
        "purchased": true,
        "publishDate": "2017-04-06 20:19:37",
        "purchaseDate": "2017-02-16 09:20:47",
        "usefull": 0,
        "useless": 0
    },
    {
        "opinionId": "11087747",
        "author": "Kamil",
        "rcmd": true,
        "stars": 5.0,
        "content": "Produkt bardzo dobry.",
        "pros": [],
        "cons": [],
        "purchased": true,
        "publishDate": "2019-09-27 09:24:13",
        "purchaseDate": "2019-08-29 09:01:33",
        "usefull": 0,
        "useless": 0
    },
    {
        "opinionId": "8173495",
        "author": "Hania",
        "rcmd": true,
        "stars": 5.0,
        "content": "Wszystko ok. Polecam",
        "pros": [],
        "cons": [],
        "purchased": true,
        "publishDate": "2018-07-24 14:57:04",
        "purchaseDate": "2018-06-24 23:00:51",
        "usefull": 0,
        "useless": 0
    },
    {
        "opinionId": "8330891",
        "author": "JB",
        "rcmd": true,
        "stars": 4.0,
        "content": "Bardzo dobry towar",
        "pros": [],
        "cons": [],
        "purchased": true,
        "publishDate": "2018-09-10 10:03:18",
        "purchaseDate": "2018-08-09 08:59:27",
        "usefull": 0,
        "useless": 0
    },
    {
        "opinionId": "4386973",
        "author": "grzesiek",
        "rcmd": true,
        "stars": 5.0,
        "content": "ergonomia i wygoda",
        "pros": [],
        "cons": [],
        "purchased": true,
        "publishDate": "2017-01-30 09:04:40",
        "purchaseDate": "2016-12-07 09:34:49",
        "usefull": 0,
        "useless": 0
    },
    {
        "opinionId": "11632026",
        "author": "Użytkownik Ceneo",
        "rcmd": true,
        "stars": 5.0,
        "content": "solidne wykonanie",
        "pros": [],
        "cons": [],
        "purchased": true,
        "publishDate": "2020-01-23 19:30:28",
        "purchaseDate": "2019-12-18 21:51:18",
        "usefull": 0,
        "useless": 0
    },
    {
        "opinionId": "13658309",
        "author": "k...a",
        "rcmd": true,
        "stars": 4.5,
        "content": "zgodnie z opisem",
        "pros": [],
        "cons": [],
        "purchased": true,
        "publishDate": "2020-12-28 07:48:46",
        "purchaseDate": "2020-11-13 08:34:25",
        "usefull": 0,
        "useless": 0
    },
    {
        "opinionId": "13830967",
        "author": "s...t",
        "rcmd": true,
        "stars": 5.0,
        "content": "wygodne,lekkie",
        "pros": [
            "jakość",
            "regulowane podlokietniki",
            "wygląd",
            "wygoda"
        ],
        "cons": [],
        "purchased": true,
        "publishDate": "2021-01-25 09:28:16",
        "purchaseDate": "2020-12-21 14:32:21",
        "usefull": 0,
        "useless": 0
    },
    {
        "opinionId": "10443364",
        "author": "MAŁGORZATA",
        "rcmd": true,
        "stars": 4.5,
        "content": "polecam w 100%",
        "pros": [],
        "cons": [],
        "purchased": true,
        "publishDate": "2019-04-25 13:01:25",
        "purchaseDate": "2019-03-20 09:50:38",
        "usefull": 0,
        "useless": 0
    },
    {
        "opinionId": "12693941",
        "author": "t...9",
        "rcmd": true,
        "stars": 4.5,
        "content": "Super krzesło",
        "pros": [
            "jakość",
            "regulowane podlokietniki",
            "wygląd",
            "wygoda"
        ],
        "cons": [],
        "purchased": true,
        "publishDate": "2020-06-22 22:16:54",
        "purchaseDate": "2020-05-14 18:23:53",
        "usefull": 0,
        "useless": 0
    },
    {
        "opinionId": "12509376",
        "author": "m...a",
        "rcmd": true,
        "stars": 5.0,
        "content": "Fotel super.",
        "pros": [],
        "cons": [],
        "purchased": true,
        "publishDate": "2020-05-25 09:50:21",
        "purchaseDate": "2020-04-22 09:45:33",
        "usefull": 0,
        "useless": 0
    },
    {
        "opinionId": "12607850",
        "author": "w...l",
        "rcmd": true,
        "stars": 5.0,
        "content": "Wszystko Ok",
        "pros": [
            "jakość",
            "regulowane podlokietniki",
            "wygląd",
            "wygoda"
        ],
        "cons": [],
        "purchased": true,
        "publishDate": "2020-06-08 09:45:09",
        "purchaseDate": "2020-05-08 13:16:04",
        "usefull": 0,
        "useless": 0
    },
    {
        "opinionId": "11988031",
        "author": "Użytkownik Ceneo",
        "rcmd": null,
        "stars": 3.0,
        "content": "Słabe podparcie odcinka lędźwiowego, trzeba stosować dodatkową poduszkę bo bolą plecy po całodniowym siedzeniu",
        "pros": [],
        "cons": [],
        "purchased": true,
        "publishDate": "2020-03-26 09:39:41",
        "purchaseDate": "2020-02-26 12:43:42",
        "usefull": 0,
        "useless": 0
    },
    {
        "opinionId": "11717191",
        "author": "Użytkownik Ceneo",
        "rcmd": true,
        "stars": 5.0,
        "content": "Wszystko ok",
        "pros": [],
        "cons": [],
        "purchased": true,
        "publishDate": "2020-02-10 09:08:23",
        "purchaseDate": "2020-01-10 15:32:37",
        "usefull": 0,
        "useless": 0
    },
    {
        "opinionId": "11087513",
        "author": "piotr",
        "rcmd": null,
        "stars": 3.0,
        "content": "niepotrzebnie zastosowano sztuczną skórę na siedzisku, dziwnie ustawione siedzisko - nie jest poziomo ustawione",
        "pros": [],
        "cons": [],
        "purchased": true,
        "publishDate": "2019-09-27 08:24:50",
        "purchaseDate": "2019-08-26 22:15:27",
        "usefull": 0,
        "useless": 0
    },
    {
        "opinionId": "4521607",
        "author": "Dawid",
        "rcmd": true,
        "stars": 5.0,
        "content": "5 gwiazdek",
        "pros": [],
        "cons": [],
        "purchased": true,
        "publishDate": "2017-03-25 14:29:36",
        "purchaseDate": "2017-02-09 21:12:25",
        "usefull": 0,
        "useless": 0
    },
    {
        "opinionId": "4466658",
        "author": "AB",
        "rcmd": true,
        "stars": 5.0,
        "content": "Zadowolony",
        "pros": [],
        "cons": [],
        "purchased": true,
        "publishDate": "2017-03-02 09:34:58",
        "purchaseDate": "2017-02-01 11:44:48",
        "usefull": 0,
        "useless": 0
    },
    {
        "opinionId": "13734834",
        "author": "p...i",
        "rcmd": true,
        "stars": 4.0,
        "content": "jest ok.",
        "pros": [],
        "cons": [],
        "purchased": true,
        "publishDate": "2021-01-08 09:49:08",
        "purchaseDate": "2020-12-01 16:47:48",
        "usefull": 0,
        "useless": 0
    },
    {
        "opinionId": "12164186",
        "author": "Użytkownik Ceneo",
        "rcmd": true,
        "stars": 5.0,
        "content": "może być",
        "pros": [],
        "cons": [],
        "purchased": true,
        "publishDate": "2020-04-16 13:17:01",
        "purchaseDate": "2020-03-17 15:59:52",
        "usefull": 0,
        "useless": 0
    },
    {
        "opinionId": "13410767",
        "author": "a...7",
        "rcmd": true,
        "stars": 5.0,
        "content": "Polecam",
        "pros": [],
        "cons": [],
        "purchased": true,
        "publishDate": "2020-11-19 20:19:01",
        "purchaseDate": "2020-10-19 21:01:42",
        "usefull": 0,
        "useless": 0
    },
    {
        "opinionId": "12695996",
        "author": "b...o",
        "rcmd": true,
        "stars": 5.0,
        "content": "B.DOBRY",
        "pros": [
            "czaami skrzypi",
            "jakość",
            "-jakość",
            "-materiał siateczkowy",
            "regulowane podlokietniki",
            "-regulowane podłokietniki",
            "siatkowe",
            "wygląd",
            "-wygląd",
            "wygoda",
            "-wygoda"
        ],
        "cons": [],
        "purchased": true,
        "publishDate": "2020-06-23 10:31:08",
        "purchaseDate": "2020-05-22 14:57:39",
        "usefull": 0,
        "useless": 0
    },
    {
        "opinionId": "12029992",
        "author": "Marzena",
        "rcmd": true,
        "stars": 5.0,
        "content": "Polecam",
        "pros": [],
        "cons": [],
        "purchased": true,
        "publishDate": "2020-04-01 07:42:00",
        "purchaseDate": "2020-03-02 13:38:28",
        "usefull": 0,
        "useless": 0
    },
    {
        "opinionId": "8382830",
        "author": "Piotr",
        "rcmd": true,
        "stars": 5.0,
        "content": "Wygodne",
        "pros": [],
        "cons": [],
        "purchased": true,
        "publishDate": "2018-09-26 16:20:45",
        "purchaseDate": "2018-08-20 12:41:22",
        "usefull": 0,
        "useless": 0
    },
    {
        "opinionId": "12738532",
        "author": "k...z",
        "rcmd": true,
        "stars": 5.0,
        "content": "Super",
        "pros": [
            "jakość",
            "regulowane podlokietniki",
            "wygląd",
            "wygoda"
        ],
        "cons": [],
        "purchased": true,
        "publishDate": "2020-06-30 20:47:29",
        "purchaseDate": "2020-05-24 09:56:45",
        "usefull": 0,
        "useless": 0
    },
    {
        "opinionId": "8241703",
        "author": "Jarecki",
        "rcmd": true,
        "stars": 5.0,
        "content": "Dobry",
        "pros": [],
        "cons": [],
        "purchased": true,
        "publishDate": "2018-08-13 10:35:14",
        "purchaseDate": "2018-07-13 11:24:41",
        "usefull": 0,
        "useless": 0
    },
    {
        "opinionId": "4545982",
        "author": "Wojtek",
        "rcmd": true,
        "stars": 4.5,
        "content": "Super",
        "pros": [],
        "cons": [],
        "purchased": true,
        "publishDate": "2017-04-05 09:52:10",
        "purchaseDate": "2017-03-21 08:14:35",
        "usefull": 0,
        "useless": 0
    },
    {
        "opinionId": "4429508",
        "author": "PSSE",
        "rcmd": true,
        "stars": 5.0,
        "content": "Super",
        "pros": [],
        "cons": [],
        "purchased": true,
        "publishDate": "2017-02-14 11:17:37",
        "purchaseDate": "2017-01-09 12:27:27",
        "usefull": 0,
        "useless": 0
    },
    {
        "opinionId": "11652043",
        "author": "Użytkownik Ceneo",
        "rcmd": true,
        "stars": 4.5,
        "content": "++++",
        "pros": [],
        "cons": [],
        "purchased": true,
        "publishDate": "2020-01-28 12:47:47",
        "purchaseDate": "2019-12-10 15:00:56",
        "usefull": 0,
        "useless": 0
    },
    {
        "opinionId": "12291917",
        "author": "Użytkownik Ceneo",
        "rcmd": true,
        "stars": 4.0,
        "content": "ok",
        "pros": [],
        "cons": [],
        "purchased": true,
        "publishDate": "2020-04-29 16:29:26",
        "purchaseDate": "2020-03-30 20:38:25",
        "usefull": 0,
        "useless": 0
    },
    {
        "opinionId": "10549920",
        "author": "Zdzisław",
        "rcmd": true,
        "stars": 4.0,
        "content": "ok",
        "pros": [],
        "cons": [],
        "purchased": true,
        "publishDate": "2019-05-20 22:55:13",
        "purchaseDate": "2019-05-06 20:14:49",
        "usefull": 0,
        "useless": 0
    },
    {
        "opinionId": "10328268",
        "author": "Kasia",
        "rcmd": true,
        "stars": 4.5,
        "content": "OK",
        "pros": [],
        "cons": [],
        "purchased": true,
        "publishDate": "2019-03-31 16:48:58",
        "purchaseDate": "2019-03-01 10:52:54",
        "usefull": 0,
        "useless": 0
    }
]